<annotation>
	<folder>pingceji</folder>
	<filename>140.jpg</filename>
	<path>/home/xxt/pingceji/140.jpg</path>
	<source>
		<database>Unknown</database>
	</source>
	<size>
		<width>2048</width>
		<height>2048</height>
		<depth>3</depth>
	</size>
	<segmented>0</segmented>
	<object>
		<name>pl20</name>
		<pose>Unspecified</pose>
		<truncated>0</truncated>
		<difficult>0</difficult>
		<bndbox>
			<xmin>756</xmin>
			<ymin>578</ymin>
			<xmax>926</xmax>
			<ymax>821</ymax>
		</bndbox>
	</object>
	<object>
		<name>pn</name>
		<pose>Unspecified</pose>
		<truncated>0</truncated>
		<difficult>0</difficult>
		<bndbox>
			<xmin>761</xmin>
			<ymin>826</ymin>
			<xmax>921</xmax>
			<ymax>1072</ymax>
		</bndbox>
	</object>
</annotation>
